odoo8_addon_product_sale_tax_price_included-8.0.1.0.1-nspkg.pth
odoo_addons/product_sale_tax_price_included/README.rst
odoo_addons/product_sale_tax_price_included/__init__.py
odoo_addons/product_sale_tax_price_included/__openerp__.py
odoo_addons/product_sale_tax_price_included/demo/account_tax_demo.xml
odoo_addons/product_sale_tax_price_included/demo/product_template_demo.xml
odoo_addons/product_sale_tax_price_included/i18n/fr.po
odoo_addons/product_sale_tax_price_included/i18n/product_sale_tax_price_included.pot
odoo_addons/product_sale_tax_price_included/models/__init__.py
odoo_addons/product_sale_tax_price_included/models/product_template.py
odoo_addons/product_sale_tax_price_included/readme/CONTRIBUTORS.rst
odoo_addons/product_sale_tax_price_included/readme/DESCRIPTION.rst
odoo_addons/product_sale_tax_price_included/static/description/icon.png
odoo_addons/product_sale_tax_price_included/static/description/index.html
odoo_addons/product_sale_tax_price_included/static/description/product_different_prices.png
odoo_addons/product_sale_tax_price_included/static/description/product_tax_excluded.png
odoo_addons/product_sale_tax_price_included/static/description/product_tax_included.png
odoo_addons/product_sale_tax_price_included/static/description/product_tax_included_and_not.png
odoo_addons/product_sale_tax_price_included/static/description/taxes_creation.png
odoo_addons/product_sale_tax_price_included/views/product_template.xml
odoo8_addon_product_sale_tax_price_included-8.0.1.0.1.dist-info/METADATA
odoo8_addon_product_sale_tax_price_included-8.0.1.0.1.dist-info/WHEEL
odoo8_addon_product_sale_tax_price_included-8.0.1.0.1.dist-info/namespace_packages.txt
odoo8_addon_product_sale_tax_price_included-8.0.1.0.1.dist-info/top_level.txt
odoo8_addon_product_sale_tax_price_included-8.0.1.0.1.dist-info/RECORD
