Metadata-Version: 2.1
Name: odoo8-addon-product-sale-tax-price-included
Version: 8.0.1.0.1
Summary: See product sale price With and without Tax
Home-page: https://github.com/OCA/product-attribute
Author: GRAP, Odoo Community Association (OCA)
Author-email: support@odoo-community.org
License: AGPL-3
Platform: UNKNOWN
Classifier: Programming Language :: Python
Classifier: Framework :: Odoo
Classifier: License :: OSI Approved :: GNU Affero General Public License v3
Requires-Python: ~=2.7
Requires-Dist: odoo (<9.0a,>=8.0a)
